ablinfer/__init__.py
ablinfer/base.py
ablinfer/cli.py
ablinfer/constants.py
ablinfer/docker/__init__.py
ablinfer/docker/_docker_patch.py
ablinfer/docker/dispatchdocker.py
ablinfer/docker/docker_helper.py
ablinfer/inferserver/__init__.py
ablinfer/inferserver/default_settings.py
ablinfer/inferserver/util.py
ablinfer/inferserver/views.py
ablinfer/model/__init__.py
ablinfer/model/__main__.py
ablinfer/model/config.py
ablinfer/model/normalize.py
ablinfer/model/typing_shim.py
ablinfer/model/update.py
ablinfer/processing/__init__.py
ablinfer/processing/base.py
ablinfer/remote/__init__.py
ablinfer/remote/remote.py
ablinfer/remote/util.py
ablinfer/slicer/__init__.py
ablinfer/slicer/dispatchslicer.py
ablinfer/slicer/processing.py
ablinfer-1.2.3.dist-info/LICENSE
ablinfer-1.2.3.dist-info/METADATA
ablinfer-1.2.3.dist-info/WHEEL
ablinfer-1.2.3.dist-info/top_level.txt
ablinfer-1.2.3.dist-info/RECORD
