Metadata-Version: 2.1
Name: ablinfer
Version: 1.2.3
Summary: Library for dispatching medical images to registration and segmentation toolkits.
Home-page: https://github.com/Auditory-Biophysics-Lab/ablinfer
Author: Ben Connors
License: UNKNOWN
Platform: UNKNOWN
Classifier: Programming Language :: Python :: 3
Classifier: Operating System :: OS Independent
Requires-Python: >=3.3
Requires-Dist: docker (>=4.3.0)
Requires-Dist: requests
